odoo/addons/delivery_line_sale_line_position/README.rst
odoo/addons/delivery_line_sale_line_position/__init__.py
odoo/addons/delivery_line_sale_line_position/__manifest__.py
odoo/addons/delivery_line_sale_line_position/i18n/delivery_line_sale_line_position.pot
odoo/addons/delivery_line_sale_line_position/i18n/it.po
odoo/addons/delivery_line_sale_line_position/models/__init__.py
odoo/addons/delivery_line_sale_line_position/models/stock_move.py
odoo/addons/delivery_line_sale_line_position/models/stock_move_line.py
odoo/addons/delivery_line_sale_line_position/readme/CONTRIBUTORS.rst
odoo/addons/delivery_line_sale_line_position/readme/CREDITS.rst
odoo/addons/delivery_line_sale_line_position/readme/DESCRIPTION.rst
odoo/addons/delivery_line_sale_line_position/report/report_deliveryslip.xml
odoo/addons/delivery_line_sale_line_position/static/description/icon.png
odoo/addons/delivery_line_sale_line_position/static/description/index.html
odoo/addons/delivery_line_sale_line_position/views/stock_move.xml
odoo/addons/delivery_line_sale_line_position/views/stock_picking.xml
odoo14_addon_delivery_line_sale_line_position-14.0.1.0.1.dev6.dist-info/METADATA
odoo14_addon_delivery_line_sale_line_position-14.0.1.0.1.dev6.dist-info/WHEEL
odoo14_addon_delivery_line_sale_line_position-14.0.1.0.1.dev6.dist-info/top_level.txt
odoo14_addon_delivery_line_sale_line_position-14.0.1.0.1.dev6.dist-info/RECORD
